window2video/README.MD
window2video/__init__.py
window2video/requirements.txt
window2video/thirdparty.json
window2video-0.11.dist-info/LICENSE.rst
window2video-0.11.dist-info/METADATA
window2video-0.11.dist-info/WHEEL
window2video-0.11.dist-info/top_level.txt
window2video-0.11.dist-info/RECORD
